study_reminders/__init__.py
study_reminders/__main__.py
study_reminders/logger.py
study_reminders/reminder_generator.py
study_reminders/reminder_sender.py
study_reminders/scheduler.py
study_reminders/students.py
study_reminders/students_manager.py
study_reminders-1.0.dist-info/METADATA
study_reminders-1.0.dist-info/WHEEL
study_reminders-1.0.dist-info/top_level.txt
study_reminders-1.0.dist-info/RECORD
