Metadata-Version: 2.4
Name: study_reminders
Version: 1.0
Summary: A simple student reminder app
Home-page: https://github.com/bilal99-coder/study_reminder
Author: Bilal Sahli
Author-email: bisah2204@oslomet.no
Requires-Dist: schedule
Requires-Dist: importlib-metadata; python_version > "3.10"
Dynamic: author
Dynamic: author-email
Dynamic: home-page
Dynamic: requires-dist
Dynamic: summary
